europy2017.py
europy2017-0.1.dist-info/LICENSE
europy2017-0.1.dist-info/WHEEL
europy2017-0.1.dist-info/METADATA
europy2017-0.1.dist-info/RECORD
