Metadata-Version: 1.2
Name: europy2017
Version: 0.1
Summary: Example package for EuroPython 2017
Home-page: https://github.com/takluyver/europy2017
License: UNKNOWN
Author: Thomas Kluyver
Author-email: thomas@kluyver.me.uk
Classifier: License :: OSI Approved :: MIT License
